azure/functions/extension/base/__init__.py
azure/functions/extension/base/meta.py
azure/functions/extension/base/sdkType.py
azure/functions/extension/base/utils.py
azure/functions/extension/base/web.py
azure_functions_extension_base-1.0.0a6.dist-info/LICENSE
azure_functions_extension_base-1.0.0a6.dist-info/METADATA
azure_functions_extension_base-1.0.0a6.dist-info/WHEEL
azure_functions_extension_base-1.0.0a6.dist-info/top_level.txt
azure_functions_extension_base-1.0.0a6.dist-info/RECORD
